python123/__init__.py
python123/login.py
python123-0.0.1.dist-info/LICENSE
python123-0.0.1.dist-info/METADATA
python123-0.0.1.dist-info/WHEEL
python123-0.0.1.dist-info/top_level.txt
python123-0.0.1.dist-info/RECORD
