Metadata-Version: 2.1
Name: python123
Version: 0.0.1
Summary: python123 平台的 Python SDK
Home-page: https://github.com/xuehangcang
Author: Xuehang Cang
Author-email: xuehangcang@outlook.com
Keywords: requests
Classifier: Programming Language :: Python :: 3
Classifier: Operating System :: Unix
Classifier: Operating System :: MacOS :: MacOS X
Classifier: Operating System :: Microsoft :: Windows
License-File: LICENSE
Requires-Dist: requests
